MANIFEST.in
requirements.txt
setup.py
bugle/__init__.py
bugle/bugle.py
bugle/entry.py
bugle/meta.py
bugle_sites.egg-info/PKG-INFO
bugle_sites.egg-info/SOURCES.txt
bugle_sites.egg-info/dependency_links.txt
bugle_sites.egg-info/not-zip-safe
bugle_sites.egg-info/requires.txt
bugle_sites.egg-info/top_level.txt