Metadata-Version: 1.1
Name: bugle-sites
Version: 0.0.4
Summary: static sites from markdown and yaml
Home-page: https://github.com/yosemitebandit/bugle
Author: Matt Ball
Author-email: matt.ball.2@gmail.com
License: MIT
Platform: any
Classifier: Environment :: Web Environment
Classifier: Intended Audience :: Developers
Classifier: License :: OSI Approved :: MIT License
Classifier: Operating System :: OS Independent
Classifier: Programming Language :: Python
Classifier: Topic :: Internet :: WWW/HTTP :: Dynamic Content
Classifier: Topic :: Software Development :: Libraries :: Python Modules
